dgc_modern/__init__.py
dgc_modern-1.5.dist-info/METADATA
dgc_modern-1.5.dist-info/WHEEL
dgc_modern-1.5.dist-info/top_level.txt
dgc_modern-1.5.dist-info/RECORD
