Metadata-Version: 2.4
Name: dgc_modern
Version: 1.5
Summary: DGC-Modern is Best Progress Bar Library!
Author-email: DiamondGotCat <diamondgotcat@gmail.com>
License: MIT License
Project-URL: Homepage, https://github.com/DiamondGotCat/Modern
Classifier: Programming Language :: Python :: 3
Classifier: License :: OSI Approved :: MIT License
Classifier: Operating System :: OS Independent
Requires-Python: >=3.10
